[
    {"title": "F I R S T - old shadow", "url": "https://www.youtube.com/embed/imG4BHgFXMk"},
    {"title": "Blaccer", "url": "https://www.youtube.com/embed/nH6Iml6tMvo"},
    {"title": "Break-Screw", "url": "https://www.youtube.com/embed/5UdLd3_4cQU"},
    {"title": "KURPAR-SHOW", "url": "https://www.youtube.com/embed/QIExM9XLDTs"},
    {"title": "C-Max&GHOST funny moment on training", "url": "https://www.youtube.com/embed/vlC3l2Bqdg4"},
    {"title": "Run", "url": "https://www.youtube.com/embed/wGd-pIUBtfc"},
    {"title": "Autumn video", "url": "https://www.youtube.com/embed/pv0AXDfZrKE"},
    {"title": "Уходящий 2016", "url": "https://www.youtube.com/embed/yZaMaCDvuXs"}
]
